versionizer/__init__.py
versionizer/__main__.py
versionizer/ast_differ.py
versionizer/ast_handler.py
versionizer/automated_test_executor.py
versionizer/automated_test_generator.py
versionizer/cli.py
versionizer/function_node.py
versionizer/git_handler.py
versionizer/parsed_ast_builder.py
versionizer/utils.py
versionizer/versionizer.py
versionizer-0.1.3.dist-info/LICENSE
versionizer-0.1.3.dist-info/WHEEL
versionizer-0.1.3.dist-info/METADATA
versionizer-0.1.3.dist-info/RECORD
